<FileFormat>
  <FormatID>2167</FormatID>
  <FormatName>Autodesk Revit Family File</FormatName>
  <FormatVersion>2010</FormatVersion>
  <FormatTypes>Model</FormatTypes>
  <FormatDescription>Autodesk Revit is 3D modeling software. RTE (template) files and RVT (project) files are actual Revit projects. RFA (family) files and RFT (family template) files are family files that can either be loaded into a project or saved externally.</FormatDescription>
  <FileFormatIdentifier>
    <Identifier>fmt/1349</Identifier>
    <IdentifierType>PUID</IdentifierType>
  </FileFormatIdentifier>
  <ExternalSignature>
    <ExternalSignatureID>2521</ExternalSignatureID>
    <Signature>rfa</Signature>
    <SignatureType>File extension</SignatureType>
  </ExternalSignature>
  <ExternalSignature>
    <ExternalSignatureID>2522</ExternalSignatureID>
    <Signature>rft</Signature>
    <SignatureType>File extension</SignatureType>
  </ExternalSignature>
  <RelatedFormat>
    <RelationshipType>Has priority over</RelationshipType>
    <RelatedFormatID>2164</RelatedFormatID>
    <RelatedFormatName>Autodesk Revit File</RelatedFormatName>
  </RelatedFormat>
  <RelatedFormat>
    <RelationshipType>Has priority over</RelationshipType>
    <RelatedFormatID>2165</RelatedFormatID>
    <RelatedFormatName>Autodesk Revit Project File</RelatedFormatName>
  </RelatedFormat>
  <RelatedFormat>
    <RelationshipType>Has priority over</RelationshipType>
    <RelatedFormatID>2166</RelatedFormatID>
    <RelatedFormatName>Autodesk Revit Family File</RelatedFormatName>
  </RelatedFormat>
</FileFormat>