<FileFormat>
  <FormatID>1743</FormatID>
  <FormatName>Python Source Code File</FormatName>
  <FormatTypes>Text (Structured)</FormatTypes>
  <FormatDescription>A source code file written in Python that can be run by a Python interpreter. Python is a multi-paradigm, high-level general-purpose programming language which was conceived in the late 1980s as a successor to the ABC programming language. Its extensive standard library, as well as a steadily growing number of third-party modules, provides functions, classes and more for a wide range of tasks, including scientific computing, machine learning and web scraping.</FormatDescription>
  <FileFormatIdentifier>
    <Identifier>fmt/938</Identifier>
    <IdentifierType>PUID</IdentifierType>
  </FileFormatIdentifier>
  <ExternalSignature>
    <ExternalSignatureID>1894</ExternalSignatureID>
    <Signature>py</Signature>
    <SignatureType>File extension</SignatureType>
  </ExternalSignature>
</FileFormat>