<FileFormat>
  <FormatID>2729</FormatID>
  <FormatName>Maptech BSB Documentation File</FormatName>
  <FormatTypes>Text (Structured), Dataset</FormatTypes>
  <FormatDescription>BSB (or BSB/KAP) is a file format used primarily for the storage and transmission of nautical charts. Although the format is commonly known as "BSB", the main file extension is actually .kap (or sometimes .cap), though .bsb files can also optionally be used. The main image data (as raster images) is found in .kap files, possibly with multiple images in separate files being part of a multi-page chart. The .bsb file, if present, has additional data pertaining to the chart as a whole. Additional metadata is contained in associated text files, generally stored with .bsb.txt and .kap.txt double extensions, or else names ending in "_bsb.txt" and "_kap.txt".</FormatDescription>
  <FileFormatIdentifier>
    <Identifier>fmt/1875</Identifier>
    <IdentifierType>PUID</IdentifierType>
  </FileFormatIdentifier>
  <ExternalSignature>
    <ExternalSignatureID>3353</ExternalSignatureID>
    <Signature>bsb</Signature>
    <SignatureType>File extension</SignatureType>
  </ExternalSignature>
  <ExternalSignature>
    <ExternalSignatureID>3354</ExternalSignatureID>
    <Signature>kap</Signature>
    <SignatureType>File extension</SignatureType>
  </ExternalSignature>
  <InternalSignature>
    <SignatureID>2217</SignatureID>
    <SignatureName>Maptech BSB Documentation File</SignatureName>
    <SignatureNote>Three BOF sequences with an offset of 0-700 for the following tags 'VER/' 'NTM/' 'CED/'</SignatureNote>
    <ByteSequence>
      <ByteSequenceID>2573</ByteSequenceID>
      <PositionType>Absolute from BOF</PositionType>
      <Offset>0</Offset>
      <MaxOffset>700</MaxOffset>
      <ByteSequenceValue>4345442F</ByteSequenceValue>
    </ByteSequence>
    <ByteSequence>
      <ByteSequenceID>2610</ByteSequenceID>
      <PositionType>Absolute from BOF</PositionType>
      <Offset>0</Offset>
      <MaxOffset>700</MaxOffset>
      <ByteSequenceValue>4E544D2F</ByteSequenceValue>
    </ByteSequence>
    <ByteSequence>
      <ByteSequenceID>2611</ByteSequenceID>
      <PositionType>Absolute from BOF</PositionType>
      <Offset>0</Offset>
      <MaxOffset>700</MaxOffset>
      <ByteSequenceValue>5645522F</ByteSequenceValue>
    </ByteSequence>
  </InternalSignature>
</FileFormat>