<FileFormat>
  <FormatID>610</FormatID>
  <FormatName>Tagged Image File Format</FormatName>
  <FormatVersion>4</FormatVersion>
  <FormatDisclosure>Full</FormatDisclosure>
  <FormatDescription>PUID deprecated. Please see fmt/353 for information on Tagged Image File Format.</FormatDescription>
  <BinaryFileFormat>Binary</BinaryFileFormat>
  <FileFormatIdentifier>
    <Identifier>fmt/8</Identifier>
    <IdentifierType>PUID</IdentifierType>
  </FileFormatIdentifier>
  <RelatedFormat>
    <RelationshipType>Has lower priority than</RelationshipType>
    <RelatedFormatID>672</RelatedFormatID>
    <RelatedFormatName>Exchangeable Image File Format (Uncompressed)</RelatedFormatName>
  </RelatedFormat>
  <RelatedFormat>
    <RelationshipType>Has lower priority than</RelationshipType>
    <RelatedFormatID>673</RelatedFormatID>
    <RelatedFormatName>Exchangeable Image File Format (Uncompressed)</RelatedFormatName>
  </RelatedFormat>
  <RelatedFormat>
    <RelationshipType>Has lower priority than</RelationshipType>
    <RelatedFormatID>752</RelatedFormatID>
    <RelatedFormatName>Exchangeable Image File Format (Uncompressed)</RelatedFormatName>
  </RelatedFormat>
</FileFormat>