<FileFormat>
  <FormatID>1804</FormatID>
  <FormatName>Krita Document Format</FormatName>
  <FormatTypes>Image (Raster)</FormatTypes>
  <FormatDescription>Krita is a free raster graphics editor. Krita's native document format is Krita Document (.kra), which is loosely based on the Open Document standard. The format is used for handling layered raster based graphics.</FormatDescription>
  <FileFormatIdentifier>
    <Identifier>application/x-krita</Identifier>
    <IdentifierType>MIME</IdentifierType>
  </FileFormatIdentifier>
  <FileFormatIdentifier>
    <Identifier>fmt/999</Identifier>
    <IdentifierType>PUID</IdentifierType>
  </FileFormatIdentifier>
  <ExternalSignature>
    <ExternalSignatureID>1978</ExternalSignatureID>
    <Signature>kra</Signature>
    <SignatureType>File extension</SignatureType>
  </ExternalSignature>
</FileFormat>