<FileFormat>
  <FormatID>2241</FormatID>
  <FormatName>HP TRIM Outlook Saved Message File</FormatName>
  <FormatTypes>Text (Structured)</FormatTypes>
  <FormatDescription>The HP TRIM Outlook Saved Message File is a saved message file from Outlook, associated with the EDRMS software, formerly known as HP TRIM document and records management, now re-named to Micro Focus Content Manager. There are several versions of this software with versions prior to 7.12 saving this file with an extension .mbx and versions 7.12 and later using extension .vmbx.</FormatDescription>
  <FileFormatIdentifier>
    <Identifier>fmt/1423</Identifier>
    <IdentifierType>PUID</IdentifierType>
  </FileFormatIdentifier>
  <ExternalSignature>
    <ExternalSignatureID>2619</ExternalSignatureID>
    <Signature>vmbx</Signature>
    <SignatureType>File extension</SignatureType>
  </ExternalSignature>
  <ExternalSignature>
    <ExternalSignatureID>2972</ExternalSignatureID>
    <Signature>mbx</Signature>
    <SignatureType>File extension</SignatureType>
  </ExternalSignature>
</FileFormat>