<FileFormat>
  <FormatID>2238</FormatID>
  <FormatName>Corel Print House/Print Office Document</FormatName>
  <FormatVersion>4</FormatVersion>
  <FormatTypes>Presentation</FormatTypes>
  <FormatDescription>Corel Print House is a desktop publishing application. A software product called Corel Print Office shared the same underlying format.</FormatDescription>
  <FileFormatIdentifier>
    <Identifier>fmt/1420</Identifier>
    <IdentifierType>PUID</IdentifierType>
  </FileFormatIdentifier>
  <ExternalSignature>
    <ExternalSignatureID>2608</ExternalSignatureID>
    <Signature>cph</Signature>
    <SignatureType>File extension</SignatureType>
  </ExternalSignature>
  <ExternalSignature>
    <ExternalSignatureID>2609</ExternalSignatureID>
    <Signature>cpd</Signature>
    <SignatureType>File extension</SignatureType>
  </ExternalSignature>
  <ExternalSignature>
    <ExternalSignatureID>2610</ExternalSignatureID>
    <Signature>cpo</Signature>
    <SignatureType>File extension</SignatureType>
  </ExternalSignature>
</FileFormat>