<FileFormat>
  <FormatID>105852131</FormatID>
  <FormatName>STereoLithography (binary) (gen)</FormatName>
  <FileFormatIdentifier>
    <Identifier>wikidata/105852131</Identifier>
    <IdentifierType>PUID</IdentifierType>
  </FileFormatIdentifier>
  <FileFormatIdentifier>
    <Identifier>application/octet-stream</Identifier>
    <IdentifierType>MIME</IdentifierType>
  </FileFormatIdentifier>
  <ExternalSignature>
    <ExternalSignatureID>0</ExternalSignatureID>
    <Signature>stl</Signature>
    <SignatureType>File extension</SignatureType>
  </ExternalSignature>
  <InternalSignature>
    <SignatureID>0</SignatureID>
    <SignatureName>STereoLithography (binary) (gen)</SignatureName>
    <ByteSequence>
      <ByteSequenceID>0</ByteSequenceID>
      <PositionType>Absolute from BOF</PositionType>
      <Offset>0</Offset>
      <ByteSequenceValue>62696E6172792073746C2066696C6520</ByteSequenceValue>
    </ByteSequence>
  </InternalSignature>
</FileFormat>