<FileFormat>
  <FormatID>50825843</FormatID>
  <FormatName>AVCHD Index File</FormatName>
  <FileFormatIdentifier>
    <Identifier>wikidata/50825843</Identifier>
    <IdentifierType>PUID</IdentifierType>
  </FileFormatIdentifier>
  <ExternalSignature>
    <ExternalSignatureID>0</ExternalSignatureID>
    <Signature>bdm</Signature>
    <SignatureType>File extension</SignatureType>
  </ExternalSignature>
  <ExternalSignature>
    <ExternalSignatureID>0</ExternalSignatureID>
    <Signature>bdmv</Signature>
    <SignatureType>File extension</SignatureType>
  </ExternalSignature>
</FileFormat>