<FileFormat>
  <FormatID>17175739</FormatID>
  <FormatName>comic book archive, RAR container</FormatName>
  <FileFormatIdentifier>
    <Identifier>wikidata/17175739</Identifier>
    <IdentifierType>PUID</IdentifierType>
  </FileFormatIdentifier>
  <FileFormatIdentifier>
    <Identifier>application/vnd.comicbook-rar</Identifier>
    <IdentifierType>MIME</IdentifierType>
  </FileFormatIdentifier>
  <ExternalSignature>
    <ExternalSignatureID>0</ExternalSignatureID>
    <Signature>cbr</Signature>
    <SignatureType>File extension</SignatureType>
  </ExternalSignature>
</FileFormat>