<FileFormat>
  <FormatID>105859452</FormatID>
  <FormatName>Qt Resource Collection</FormatName>
  <FileFormatIdentifier>
    <Identifier>wikidata/105859452</Identifier>
    <IdentifierType>PUID</IdentifierType>
  </FileFormatIdentifier>
  <FileFormatIdentifier>
    <Identifier>text/xml</Identifier>
    <IdentifierType>MIME</IdentifierType>
  </FileFormatIdentifier>
  <ExternalSignature>
    <ExternalSignatureID>0</ExternalSignatureID>
    <Signature>qrc</Signature>
    <SignatureType>File extension</SignatureType>
  </ExternalSignature>
</FileFormat>