<FileFormat>
  <FormatID>59693916</FormatID>
  <FormatName>QuadriSpace format</FormatName>
  <FileFormatIdentifier>
    <Identifier>wikidata/59693916</Identifier>
    <IdentifierType>PUID</IdentifierType>
  </FileFormatIdentifier>
  <ExternalSignature>
    <ExternalSignatureID>0</ExternalSignatureID>
    <Signature>qsd</Signature>
    <SignatureType>File extension</SignatureType>
  </ExternalSignature>
  <ExternalSignature>
    <ExternalSignatureID>0</ExternalSignatureID>
    <Signature>qsl</Signature>
    <SignatureType>File extension</SignatureType>
  </ExternalSignature>
  <ExternalSignature>
    <ExternalSignatureID>0</ExternalSignatureID>
    <Signature>qsm</Signature>
    <SignatureType>File extension</SignatureType>
  </ExternalSignature>
  <ExternalSignature>
    <ExternalSignatureID>0</ExternalSignatureID>
    <Signature>qst</Signature>
    <SignatureType>File extension</SignatureType>
  </ExternalSignature>
</FileFormat>