<FileFormat>
  <FormatID>105857292</FormatID>
  <FormatName>EnCase forensics Hash</FormatName>
  <FileFormatIdentifier>
    <Identifier>wikidata/105857292</Identifier>
    <IdentifierType>PUID</IdentifierType>
  </FileFormatIdentifier>
  <FileFormatIdentifier>
    <Identifier>application/octet-stream</Identifier>
    <IdentifierType>MIME</IdentifierType>
  </FileFormatIdentifier>
  <ExternalSignature>
    <ExternalSignatureID>0</ExternalSignatureID>
    <Signature>hash</Signature>
    <SignatureType>File extension</SignatureType>
  </ExternalSignature>
  <InternalSignature>
    <SignatureID>0</SignatureID>
    <SignatureName>EnCase forensics Hash</SignatureName>
    <ByteSequence>
      <ByteSequenceID>0</ByteSequenceID>
      <PositionType>Absolute from BOF</PositionType>
      <Offset>0</Offset>
      <ByteSequenceValue>484153480D0AFF00</ByteSequenceValue>
    </ByteSequence>
  </InternalSignature>
</FileFormat>