<FileFormat>
  <FormatID>105853077</FormatID>
  <FormatName>phpMyAdmin SQL dump</FormatName>
  <FileFormatIdentifier>
    <Identifier>wikidata/105853077</Identifier>
    <IdentifierType>PUID</IdentifierType>
  </FileFormatIdentifier>
  <ExternalSignature>
    <ExternalSignatureID>0</ExternalSignatureID>
    <Signature>sql</Signature>
    <SignatureType>File extension</SignatureType>
  </ExternalSignature>
  <InternalSignature>
    <SignatureID>0</SignatureID>
    <SignatureName>phpMyAdmin SQL dump</SignatureName>
    <ByteSequence>
      <ByteSequenceID>0</ByteSequenceID>
      <PositionType>Absolute from BOF</PositionType>
      <Offset>0</Offset>
      <ByteSequenceValue>2D2D207068704D7941646D696E2053514C2044756D70</ByteSequenceValue>
    </ByteSequence>
  </InternalSignature>
</FileFormat>