<FileFormat>
  <FormatID>50413899</FormatID>
  <FormatName>Lightwright 3 Show File</FormatName>
  <FileFormatIdentifier>
    <Identifier>wikidata/50413899</Identifier>
    <IdentifierType>PUID</IdentifierType>
  </FileFormatIdentifier>
  <FileFormatIdentifier>
    <Identifier>application/octet-stream</Identifier>
    <IdentifierType>MIME</IdentifierType>
  </FileFormatIdentifier>
  <ExternalSignature>
    <ExternalSignatureID>0</ExternalSignatureID>
    <Signature>lw3</Signature>
    <SignatureType>File extension</SignatureType>
  </ExternalSignature>
</FileFormat>