<FileFormat>
  <FormatID>105867436</FormatID>
  <FormatName>Drishti Processed Volume (header)</FormatName>
  <FileFormatIdentifier>
    <Identifier>wikidata/105867436</Identifier>
    <IdentifierType>PUID</IdentifierType>
  </FileFormatIdentifier>
  <FileFormatIdentifier>
    <Identifier>text/xml</Identifier>
    <IdentifierType>MIME</IdentifierType>
  </FileFormatIdentifier>
  <ExternalSignature>
    <ExternalSignatureID>0</ExternalSignatureID>
    <Signature>nc</Signature>
    <SignatureType>File extension</SignatureType>
  </ExternalSignature>
  <InternalSignature>
    <SignatureID>0</SignatureID>
    <SignatureName>Drishti Processed Volume (header)</SignatureName>
    <ByteSequence>
      <ByteSequenceID>0</ByteSequenceID>
      <PositionType>Absolute from BOF</PositionType>
      <Offset>0</Offset>
      <ByteSequenceValue>3C21444F435459504520447269736874695F4865616465723E</ByteSequenceValue>
    </ByteSequence>
  </InternalSignature>
</FileFormat>