<FileFormat>
  <FormatID>105861478</FormatID>
  <FormatName>Skunny Kart Library game data</FormatName>
  <FileFormatIdentifier>
    <Identifier>wikidata/105861478</Identifier>
    <IdentifierType>PUID</IdentifierType>
  </FileFormatIdentifier>
  <FileFormatIdentifier>
    <Identifier>application/octet-stream</Identifier>
    <IdentifierType>MIME</IdentifierType>
  </FileFormatIdentifier>
  <ExternalSignature>
    <ExternalSignatureID>0</ExternalSignatureID>
    <Signature>lid</Signature>
    <SignatureType>File extension</SignatureType>
  </ExternalSignature>
  <InternalSignature>
    <SignatureID>0</SignatureID>
    <SignatureName>Skunny Kart Library game data</SignatureName>
    <ByteSequence>
      <ByteSequenceID>0</ByteSequenceID>
      <PositionType>Absolute from BOF</PositionType>
      <Offset>0</Offset>
      <ByteSequenceValue>534B554E4E59204B415254204C4942201A</ByteSequenceValue>
    </ByteSequence>
  </InternalSignature>
</FileFormat>