<FileFormat>
  <FormatID>104876349</FormatID>
  <FormatName>JCAMP-DX</FormatName>
  <FileFormatIdentifier>
    <Identifier>wikidata/104876349</Identifier>
    <IdentifierType>PUID</IdentifierType>
  </FileFormatIdentifier>
  <FileFormatIdentifier>
    <Identifier>chemical/x-jcamp-dx</Identifier>
    <IdentifierType>MIME</IdentifierType>
  </FileFormatIdentifier>
  <FileFormatIdentifier>
    <Identifier>chemical/x-jcamp-dx</Identifier>
    <IdentifierType>MIME</IdentifierType>
  </FileFormatIdentifier>
  <FileFormatIdentifier>
    <Identifier>chemical/x-jcamp-dx</Identifier>
    <IdentifierType>MIME</IdentifierType>
  </FileFormatIdentifier>
  <ExternalSignature>
    <ExternalSignatureID>0</ExternalSignatureID>
    <Signature>dx</Signature>
    <SignatureType>File extension</SignatureType>
  </ExternalSignature>
  <ExternalSignature>
    <ExternalSignatureID>0</ExternalSignatureID>
    <Signature>jcm</Signature>
    <SignatureType>File extension</SignatureType>
  </ExternalSignature>
  <ExternalSignature>
    <ExternalSignatureID>0</ExternalSignatureID>
    <Signature>jdx</Signature>
    <SignatureType>File extension</SignatureType>
  </ExternalSignature>
</FileFormat>