<FileFormat>
  <FormatID>83883611</FormatID>
  <FormatName>Raw Flux Image</FormatName>
  <FileFormatIdentifier>
    <Identifier>wikidata/83883611</Identifier>
    <IdentifierType>PUID</IdentifierType>
  </FileFormatIdentifier>
  <FileFormatIdentifier>
    <Identifier>application/octet-stream</Identifier>
    <IdentifierType>MIME</IdentifierType>
  </FileFormatIdentifier>
  <ExternalSignature>
    <ExternalSignatureID>0</ExternalSignatureID>
    <Signature>rfi</Signature>
    <SignatureType>File extension</SignatureType>
  </ExternalSignature>
  <InternalSignature>
    <SignatureID>0</SignatureID>
    <SignatureName>Raw Flux Image</SignatureName>
    <ByteSequence>
      <ByteSequenceID>0</ByteSequenceID>
      <PositionType>Absolute from BOF</PositionType>
      <Offset>0</Offset>
      <ByteSequenceValue>5246497B</ByteSequenceValue>
    </ByteSequence>
  </InternalSignature>
</FileFormat>