<FileFormat>
  <FormatID>105856682</FormatID>
  <FormatName>Uniform Office Format (generic)</FormatName>
  <FileFormatIdentifier>
    <Identifier>wikidata/105856682</Identifier>
    <IdentifierType>PUID</IdentifierType>
  </FileFormatIdentifier>
  <FileFormatIdentifier>
    <Identifier>text/xml</Identifier>
    <IdentifierType>MIME</IdentifierType>
  </FileFormatIdentifier>
  <ExternalSignature>
    <ExternalSignatureID>0</ExternalSignatureID>
    <Signature>uof</Signature>
    <SignatureType>File extension</SignatureType>
  </ExternalSignature>
</FileFormat>