<FileFormat>
  <FormatID>28207202</FormatID>
  <FormatName>QuickTime Image Format</FormatName>
  <FileFormatIdentifier>
    <Identifier>wikidata/28207202</Identifier>
    <IdentifierType>PUID</IdentifierType>
  </FileFormatIdentifier>
  <ExternalSignature>
    <ExternalSignatureID>0</ExternalSignatureID>
    <Signature>qif</Signature>
    <SignatureType>File extension</SignatureType>
  </ExternalSignature>
  <ExternalSignature>
    <ExternalSignatureID>0</ExternalSignatureID>
    <Signature>qtif</Signature>
    <SignatureType>File extension</SignatureType>
  </ExternalSignature>
</FileFormat>