<FileFormat>
  <FormatID>105866566</FormatID>
  <FormatName>ProbModelXML model</FormatName>
  <FileFormatIdentifier>
    <Identifier>wikidata/105866566</Identifier>
    <IdentifierType>PUID</IdentifierType>
  </FileFormatIdentifier>
  <FileFormatIdentifier>
    <Identifier>text/xml</Identifier>
    <IdentifierType>MIME</IdentifierType>
  </FileFormatIdentifier>
  <ExternalSignature>
    <ExternalSignatureID>0</ExternalSignatureID>
    <Signature>pgmx</Signature>
    <SignatureType>File extension</SignatureType>
  </ExternalSignature>
</FileFormat>