<FileFormat>
  <FormatID>28757904</FormatID>
  <FormatName>Go script</FormatName>
  <FileFormatIdentifier>
    <Identifier>wikidata/28757904</Identifier>
    <IdentifierType>PUID</IdentifierType>
  </FileFormatIdentifier>
  <FileFormatIdentifier>
    <Identifier>text/x-gosrc</Identifier>
    <IdentifierType>MIME</IdentifierType>
  </FileFormatIdentifier>
  <ExternalSignature>
    <ExternalSignatureID>0</ExternalSignatureID>
    <Signature>go</Signature>
    <SignatureType>File extension</SignatureType>
  </ExternalSignature>
</FileFormat>