<FileFormat>
  <FormatID>105858706</FormatID>
  <FormatName>Bizagi Process Modeler document</FormatName>
  <FileFormatIdentifier>
    <Identifier>wikidata/105858706</Identifier>
    <IdentifierType>PUID</IdentifierType>
  </FileFormatIdentifier>
  <ExternalSignature>
    <ExternalSignatureID>0</ExternalSignatureID>
    <Signature>bpm</Signature>
    <SignatureType>File extension</SignatureType>
  </ExternalSignature>
  <InternalSignature>
    <SignatureID>0</SignatureID>
    <SignatureName>Bizagi Process Modeler document</SignatureName>
    <ByteSequence>
      <ByteSequenceID>0</ByteSequenceID>
      <PositionType>Absolute from BOF</PositionType>
      <Offset>0</Offset>
      <ByteSequenceValue>504B0304</ByteSequenceValue>
    </ByteSequence>
  </InternalSignature>
</FileFormat>