<FileFormat>
  <FormatID>100165244</FormatID>
  <FormatName>Drawing Interchange Format (ASCII), version 2018/2019/2020</FormatName>
  <FileFormatIdentifier>
    <Identifier>wikidata/100165244</Identifier>
    <IdentifierType>PUID</IdentifierType>
  </FileFormatIdentifier>
  <FileFormatIdentifier>
    <Identifier>image/vnd.dxf</Identifier>
    <IdentifierType>MIME</IdentifierType>
  </FileFormatIdentifier>
  <ExternalSignature>
    <ExternalSignatureID>0</ExternalSignatureID>
    <Signature>dxf</Signature>
    <SignatureType>File extension</SignatureType>
  </ExternalSignature>
</FileFormat>