<FileFormat>
  <FormatID>105865307</FormatID>
  <FormatName>MS Visual C++ precompiled header</FormatName>
  <FileFormatIdentifier>
    <Identifier>wikidata/105865307</Identifier>
    <IdentifierType>PUID</IdentifierType>
  </FileFormatIdentifier>
  <ExternalSignature>
    <ExternalSignatureID>0</ExternalSignatureID>
    <Signature>pch</Signature>
    <SignatureType>File extension</SignatureType>
  </ExternalSignature>
  <InternalSignature>
    <SignatureID>0</SignatureID>
    <SignatureName>MS Visual C++ precompiled header</SignatureName>
    <ByteSequence>
      <ByteSequenceID>0</ByteSequenceID>
      <PositionType>Absolute from BOF</PositionType>
      <Offset>0</Offset>
      <ByteSequenceValue>564350434830</ByteSequenceValue>
    </ByteSequence>
  </InternalSignature>
</FileFormat>