<FileFormat>
  <FormatID>27684948</FormatID>
  <FormatName>Microsoft Publisher file format, version 16.0</FormatName>
  <FileFormatIdentifier>
    <Identifier>wikidata/27684948</Identifier>
    <IdentifierType>PUID</IdentifierType>
  </FileFormatIdentifier>
  <FileFormatIdentifier>
    <Identifier>application/vnd.ms-publisher</Identifier>
    <IdentifierType>MIME</IdentifierType>
  </FileFormatIdentifier>
  <ExternalSignature>
    <ExternalSignatureID>0</ExternalSignatureID>
    <Signature>pub</Signature>
    <SignatureType>File extension</SignatureType>
  </ExternalSignature>
</FileFormat>