<FileFormat>
  <FormatID>921895</FormatID>
  <FormatName>BBeB</FormatName>
  <FileFormatIdentifier>
    <Identifier>wikidata/921895</Identifier>
    <IdentifierType>PUID</IdentifierType>
  </FileFormatIdentifier>
  <ExternalSignature>
    <ExternalSignatureID>0</ExternalSignatureID>
    <Signature>lrf</Signature>
    <SignatureType>File extension</SignatureType>
  </ExternalSignature>
  <ExternalSignature>
    <ExternalSignatureID>0</ExternalSignatureID>
    <Signature>lrs</Signature>
    <SignatureType>File extension</SignatureType>
  </ExternalSignature>
  <ExternalSignature>
    <ExternalSignatureID>0</ExternalSignatureID>
    <Signature>lrx</Signature>
    <SignatureType>File extension</SignatureType>
  </ExternalSignature>
  <InternalSignature>
    <SignatureID>0</SignatureID>
    <SignatureName>BBeB</SignatureName>
    <ByteSequence>
      <ByteSequenceID>0</ByteSequenceID>
      <PositionType>Absolute from BOF</PositionType>
      <Offset>0</Offset>
      <ByteSequenceValue>4C0052004600</ByteSequenceValue>
    </ByteSequence>
  </InternalSignature>
  <InternalSignature>
    <SignatureID>0</SignatureID>
    <SignatureName>BBeB</SignatureName>
    <ByteSequence>
      <ByteSequenceID>0</ByteSequenceID>
      <PositionType>Absolute from BOF</PositionType>
      <Offset>0</Offset>
      <ByteSequenceValue>4C0052004600</ByteSequenceValue>
    </ByteSequence>
  </InternalSignature>
  <InternalSignature>
    <SignatureID>0</SignatureID>
    <SignatureName>BBeB</SignatureName>
    <ByteSequence>
      <ByteSequenceID>0</ByteSequenceID>
      <PositionType>Absolute from BOF</PositionType>
      <Offset>0</Offset>
      <ByteSequenceValue>4C0052004600</ByteSequenceValue>
    </ByteSequence>
  </InternalSignature>
</FileFormat>