<FileFormat>
  <FormatID>105851589</FormatID>
  <FormatName>Thrustmaster TARGET script</FormatName>
  <FileFormatIdentifier>
    <Identifier>wikidata/105851589</Identifier>
    <IdentifierType>PUID</IdentifierType>
  </FileFormatIdentifier>
  <ExternalSignature>
    <ExternalSignatureID>0</ExternalSignatureID>
    <Signature>tmc</Signature>
    <SignatureType>File extension</SignatureType>
  </ExternalSignature>
  <InternalSignature>
    <SignatureID>0</SignatureID>
    <SignatureName>Thrustmaster TARGET script</SignatureName>
    <ByteSequence>
      <ByteSequenceID>0</ByteSequenceID>
      <PositionType>Absolute from BOF</PositionType>
      <Offset>0</Offset>
      <ByteSequenceValue>696E636C75646520227461726765742E746D6822</ByteSequenceValue>
    </ByteSequence>
  </InternalSignature>
</FileFormat>