<FileFormat>
  <FormatID>390</FormatID>
  <FormatName>Volt</FormatName>
  <FileFormatIdentifier>
    <Identifier>linguist/390</Identifier>
    <IdentifierType>PUID</IdentifierType>
  </FileFormatIdentifier>
  <FileFormatIdentifier>
    <Identifier>text/x-d</Identifier>
    <IdentifierType>MIME</IdentifierType>
  </FileFormatIdentifier>
  <ExternalSignature>
    <ExternalSignatureID>0</ExternalSignatureID>
    <Signature>volt</Signature>
    <SignatureType>File extension</SignatureType>
  </ExternalSignature>
</FileFormat>