<FileFormat>
  <FormatID>143</FormatID>
  <FormatName>Groovy Server Pages</FormatName>
  <FileFormatIdentifier>
    <Identifier>linguist/143</Identifier>
    <IdentifierType>PUID</IdentifierType>
  </FileFormatIdentifier>
  <FileFormatIdentifier>
    <Identifier>application/x-jsp</Identifier>
    <IdentifierType>MIME</IdentifierType>
  </FileFormatIdentifier>
  <ExternalSignature>
    <ExternalSignatureID>0</ExternalSignatureID>
    <Signature>gsp</Signature>
    <SignatureType>File extension</SignatureType>
  </ExternalSignature>
</FileFormat>