<FileFormat>
  <FormatID>679594952</FormatID>
  <FormatName>Visual Basic 6.0</FormatName>
  <FileFormatIdentifier>
    <Identifier>linguist/679594952</Identifier>
    <IdentifierType>PUID</IdentifierType>
  </FileFormatIdentifier>
  <FileFormatIdentifier>
    <Identifier>text/x-vb</Identifier>
    <IdentifierType>MIME</IdentifierType>
  </FileFormatIdentifier>
  <ExternalSignature>
    <ExternalSignatureID>0</ExternalSignatureID>
    <Signature>bas</Signature>
    <SignatureType>File extension</SignatureType>
  </ExternalSignature>
  <ExternalSignature>
    <ExternalSignatureID>1</ExternalSignatureID>
    <Signature>cls</Signature>
    <SignatureType>File extension</SignatureType>
  </ExternalSignature>
  <ExternalSignature>
    <ExternalSignatureID>2</ExternalSignatureID>
    <Signature>ctl</Signature>
    <SignatureType>File extension</SignatureType>
  </ExternalSignature>
  <ExternalSignature>
    <ExternalSignatureID>3</ExternalSignatureID>
    <Signature>Dsr</Signature>
    <SignatureType>File extension</SignatureType>
  </ExternalSignature>
  <ExternalSignature>
    <ExternalSignatureID>4</ExternalSignatureID>
    <Signature>frm</Signature>
    <SignatureType>File extension</SignatureType>
  </ExternalSignature>
</FileFormat>