<FileFormat>
  <FormatID>302</FormatID>
  <FormatName>PureScript</FormatName>
  <FileFormatIdentifier>
    <Identifier>linguist/302</Identifier>
    <IdentifierType>PUID</IdentifierType>
  </FileFormatIdentifier>
  <FileFormatIdentifier>
    <Identifier>text/x-haskell</Identifier>
    <IdentifierType>MIME</IdentifierType>
  </FileFormatIdentifier>
  <ExternalSignature>
    <ExternalSignatureID>0</ExternalSignatureID>
    <Signature>purs</Signature>
    <SignatureType>File extension</SignatureType>
  </ExternalSignature>
</FileFormat>