<FileFormat>
  <FormatID>16843356083413255425</FormatID>
  <FormatName>scvp vp request</FormatName>
  <FileFormatIdentifier>
    <Identifier>httpd/16843356083413255425</Identifier>
    <IdentifierType>PUID</IdentifierType>
  </FileFormatIdentifier>
  <FileFormatIdentifier>
    <Identifier>application/scvp-vp-request</Identifier>
    <IdentifierType>MIME</IdentifierType>
  </FileFormatIdentifier>
  <ExternalSignature>
    <ExternalSignatureID>0</ExternalSignatureID>
    <Signature>spq</Signature>
    <SignatureType>File extension</SignatureType>
  </ExternalSignature>
</FileFormat>