<FileFormat>
  <FormatID>15216320534825696251</FormatID>
  <FormatName>hp hpgl</FormatName>
  <FileFormatIdentifier>
    <Identifier>httpd/15216320534825696251</Identifier>
    <IdentifierType>PUID</IdentifierType>
  </FileFormatIdentifier>
  <FileFormatIdentifier>
    <Identifier>application/vnd.hp-hpgl</Identifier>
    <IdentifierType>MIME</IdentifierType>
  </FileFormatIdentifier>
  <ExternalSignature>
    <ExternalSignatureID>0</ExternalSignatureID>
    <Signature>hpgl</Signature>
    <SignatureType>File extension</SignatureType>
  </ExternalSignature>
</FileFormat>