<FileFormat>
  <FormatID>15847581481070904334</FormatID>
  <FormatName>bzip2</FormatName>
  <FileFormatIdentifier>
    <Identifier>httpd/15847581481070904334</Identifier>
    <IdentifierType>PUID</IdentifierType>
  </FileFormatIdentifier>
  <FileFormatIdentifier>
    <Identifier>application/x-bzip2</Identifier>
    <IdentifierType>MIME</IdentifierType>
  </FileFormatIdentifier>
  <ExternalSignature>
    <ExternalSignatureID>0</ExternalSignatureID>
    <Signature>bz2</Signature>
    <SignatureType>File extension</SignatureType>
  </ExternalSignature>
  <ExternalSignature>
    <ExternalSignatureID>1</ExternalSignatureID>
    <Signature>boz</Signature>
    <SignatureType>File extension</SignatureType>
  </ExternalSignature>
</FileFormat>