<FileFormat>
  <FormatID>13440853329793760916</FormatID>
  <FormatName>uuencode</FormatName>
  <FileFormatIdentifier>
    <Identifier>httpd/13440853329793760916</Identifier>
    <IdentifierType>PUID</IdentifierType>
  </FileFormatIdentifier>
  <FileFormatIdentifier>
    <Identifier>text/x-uuencode</Identifier>
    <IdentifierType>MIME</IdentifierType>
  </FileFormatIdentifier>
  <ExternalSignature>
    <ExternalSignatureID>0</ExternalSignatureID>
    <Signature>uu</Signature>
    <SignatureType>File extension</SignatureType>
  </ExternalSignature>
</FileFormat>