<FileFormat>
  <FormatID>6962085545806922702</FormatID>
  <FormatName>oasis opendocument chart</FormatName>
  <ProvenanceSourceId>0</ProvenanceSourceId>
  <ProvenanceSourceDate>11 Jan 2025</ProvenanceSourceDate>
  <LastUpdatedDate>11 Jan 2025</LastUpdatedDate>
  <FileFormatIdentifier>
    <Identifier>httpd/6962085545806922702</Identifier>
    <IdentifierType>PUID</IdentifierType>
  </FileFormatIdentifier>
  <FileFormatIdentifier>
    <Identifier>application/vnd.oasis.opendocument.chart</Identifier>
    <IdentifierType>MIME</IdentifierType>
  </FileFormatIdentifier>
  <ExternalSignature>
    <ExternalSignatureID>0</ExternalSignatureID>
    <Signature>odc</Signature>
    <SignatureType>File extension</SignatureType>
  </ExternalSignature>
</FileFormat>