<FileFormat>
  <FormatID>5268943525352200654</FormatID>
  <FormatName>h264</FormatName>
  <FileFormatIdentifier>
    <Identifier>httpd/5268943525352200654</Identifier>
    <IdentifierType>PUID</IdentifierType>
  </FileFormatIdentifier>
  <FileFormatIdentifier>
    <Identifier>video/h264</Identifier>
    <IdentifierType>MIME</IdentifierType>
  </FileFormatIdentifier>
  <ExternalSignature>
    <ExternalSignatureID>0</ExternalSignatureID>
    <Signature>h264</Signature>
    <SignatureType>File extension</SignatureType>
  </ExternalSignature>
</FileFormat>