<FileFormat>
  <FormatID>7834014297002784124</FormatID>
  <FormatName>ccxml xml</FormatName>
  <FileFormatIdentifier>
    <Identifier>httpd/7834014297002784124</Identifier>
    <IdentifierType>PUID</IdentifierType>
  </FileFormatIdentifier>
  <FileFormatIdentifier>
    <Identifier>application/ccxml+xml</Identifier>
    <IdentifierType>MIME</IdentifierType>
  </FileFormatIdentifier>
  <ExternalSignature>
    <ExternalSignatureID>0</ExternalSignatureID>
    <Signature>ccxml</Signature>
    <SignatureType>File extension</SignatureType>
  </ExternalSignature>
</FileFormat>