<FileFormat>
  <FormatID>12792181662701773000</FormatID>
  <FormatName>dece zip</FormatName>
  <ProvenanceSourceId>0</ProvenanceSourceId>
  <ProvenanceSourceDate>11 Jan 2025</ProvenanceSourceDate>
  <LastUpdatedDate>11 Jan 2025</LastUpdatedDate>
  <FileFormatIdentifier>
    <Identifier>httpd/12792181662701773000</Identifier>
    <IdentifierType>PUID</IdentifierType>
  </FileFormatIdentifier>
  <FileFormatIdentifier>
    <Identifier>application/vnd.dece.zip</Identifier>
    <IdentifierType>MIME</IdentifierType>
  </FileFormatIdentifier>
  <ExternalSignature>
    <ExternalSignatureID>0</ExternalSignatureID>
    <Signature>uvz</Signature>
    <SignatureType>File extension</SignatureType>
  </ExternalSignature>
  <ExternalSignature>
    <ExternalSignatureID>1</ExternalSignatureID>
    <Signature>uvvz</Signature>
    <SignatureType>File extension</SignatureType>
  </ExternalSignature>
</FileFormat>