<FileFormat>
  <FormatID>7193524944753159053</FormatID>
  <FormatName>ms excel addin macroenabled 12</FormatName>
  <ProvenanceSourceId>0</ProvenanceSourceId>
  <ProvenanceSourceDate>11 Jan 2025</ProvenanceSourceDate>
  <LastUpdatedDate>11 Jan 2025</LastUpdatedDate>
  <FileFormatIdentifier>
    <Identifier>httpd/7193524944753159053</Identifier>
    <IdentifierType>PUID</IdentifierType>
  </FileFormatIdentifier>
  <FileFormatIdentifier>
    <Identifier>application/vnd.ms-excel.addin.macroenabled.12</Identifier>
    <IdentifierType>MIME</IdentifierType>
  </FileFormatIdentifier>
  <ExternalSignature>
    <ExternalSignatureID>0</ExternalSignatureID>
    <Signature>xlam</Signature>
    <SignatureType>File extension</SignatureType>
  </ExternalSignature>
</FileFormat>