<FileFormat>
  <FormatID>7113264481099194993</FormatID>
  <FormatName>acucobol</FormatName>
  <ProvenanceSourceId>0</ProvenanceSourceId>
  <ProvenanceSourceDate>11 Jan 2025</ProvenanceSourceDate>
  <LastUpdatedDate>11 Jan 2025</LastUpdatedDate>
  <FileFormatIdentifier>
    <Identifier>httpd/7113264481099194993</Identifier>
    <IdentifierType>PUID</IdentifierType>
  </FileFormatIdentifier>
  <FileFormatIdentifier>
    <Identifier>application/vnd.acucobol</Identifier>
    <IdentifierType>MIME</IdentifierType>
  </FileFormatIdentifier>
  <ExternalSignature>
    <ExternalSignatureID>0</ExternalSignatureID>
    <Signature>acu</Signature>
    <SignatureType>File extension</SignatureType>
  </ExternalSignature>
</FileFormat>