<FileFormat>
  <FormatID>16923033345032457</FormatID>
  <FormatName>symbian install</FormatName>
  <FileFormatIdentifier>
    <Identifier>httpd/16923033345032457</Identifier>
    <IdentifierType>PUID</IdentifierType>
  </FileFormatIdentifier>
  <FileFormatIdentifier>
    <Identifier>application/vnd.symbian.install</Identifier>
    <IdentifierType>MIME</IdentifierType>
  </FileFormatIdentifier>
  <ExternalSignature>
    <ExternalSignatureID>0</ExternalSignatureID>
    <Signature>sis</Signature>
    <SignatureType>File extension</SignatureType>
  </ExternalSignature>
  <ExternalSignature>
    <ExternalSignatureID>1</ExternalSignatureID>
    <Signature>sisx</Signature>
    <SignatureType>File extension</SignatureType>
  </ExternalSignature>
</FileFormat>