<FileFormat>
  <FormatID>17061360333974647667</FormatID>
  <FormatName>gramps xml</FormatName>
  <ProvenanceSourceId>0</ProvenanceSourceId>
  <ProvenanceSourceDate>11 Jan 2025</ProvenanceSourceDate>
  <LastUpdatedDate>11 Jan 2025</LastUpdatedDate>
  <FileFormatIdentifier>
    <Identifier>httpd/17061360333974647667</Identifier>
    <IdentifierType>PUID</IdentifierType>
  </FileFormatIdentifier>
  <FileFormatIdentifier>
    <Identifier>application/x-gramps-xml</Identifier>
    <IdentifierType>MIME</IdentifierType>
  </FileFormatIdentifier>
  <ExternalSignature>
    <ExternalSignatureID>0</ExternalSignatureID>
    <Signature>gramps</Signature>
    <SignatureType>File extension</SignatureType>
  </ExternalSignature>
</FileFormat>